pytest_manual_marker/__init__.py
pytest_manual_marker-2.0.0.0.dist-info/METADATA
pytest_manual_marker-2.0.0.0.dist-info/WHEEL
pytest_manual_marker-2.0.0.0.dist-info/entry_points.txt
pytest_manual_marker-2.0.0.0.dist-info/RECORD
