Metadata-Version: 2.1
Name: pytest_manual_marker
Version: 2.0.0.0
Summary: pytest marker for marking manual tests
Project-URL: Homepage, https://github.com/RonnyPfannschmidt/pytest-manual-marker
Author-email: Ronny Pfannschmidt <rpfannsc@redhat.com>, Martin Kourim <mkourim@redhat.com>
Keywords: manual,py.test,pytest,testing
Classifier: Development Status :: 3 - Alpha
Classifier: Framework :: Pytest
Classifier: Intended Audience :: Developers
Classifier: License :: OSI Approved :: MIT License
Classifier: Programming Language :: Python :: 3
Classifier: Programming Language :: Python :: 3.10
Classifier: Programming Language :: Python :: 3.7
Classifier: Programming Language :: Python :: 3.8
Classifier: Programming Language :: Python :: 3.9
Classifier: Topic :: Software Development :: Testing
Requires-Python: >=3.7
Requires-Dist: pytest>=7
Requires-Dist: regendoc>=0.9
